sugar/__init__.py
sugar/common/ObjectUtils.py
sugar/common/__init__.py
sugar/decorator/__init__.py
sugar/decorator/csv_decorator.py
sugar/decorator/string_decorator.py
neko233_sugar-0.0.3.dist-info/METADATA
neko233_sugar-0.0.3.dist-info/WHEEL
neko233_sugar-0.0.3.dist-info/licenses/LICENSE
neko233_sugar-0.0.3.dist-info/RECORD
